elcano/__init__.py
elcano/utils.py
elcano-0.1.0.dist-info/LICENSE
elcano-0.1.0.dist-info/METADATA
elcano-0.1.0.dist-info/WHEEL
elcano-0.1.0.dist-info/top_level.txt
elcano-0.1.0.dist-info/RECORD
