Metadata-Version: 2.1
Name: elcano
Version: 0.1.0
Summary: Visual dataset explorer
Home-page: https://github.com/juancroldan/elcano
Author: Juan C. Roldán
Author-email: juancarlos@sevilla.es
License: UNKNOWN
Platform: UNKNOWN
Classifier: Development Status :: 1 - Planning
Classifier: Intended Audience :: Developers
Classifier: Intended Audience :: Education
Classifier: Intended Audience :: End Users/Desktop
Classifier: Intended Audience :: Science/Research
Classifier: License :: OSI Approved :: MIT License
Classifier: Natural Language :: English
Classifier: Programming Language :: Python :: 3
Requires-Dist: kivy (<2.0,>=1.11.1)
Requires-Dist: keras (<3.0,>=2.3.1)
Requires-Dist: pandas (<2.0,>=1.0.3)
Requires-Dist: scikit-learn (<1.0,>=0.23.1)
